MANIFEST.in
README.md
setup.cfg
setup.py
slack_cache.py
slack_cache.egg-info/PKG-INFO
slack_cache.egg-info/SOURCES.txt
slack_cache.egg-info/dependency_links.txt
slack_cache.egg-info/not-zip-safe
slack_cache.egg-info/requires.txt
slack_cache.egg-info/top_level.txt