Metadata-Version: 1.1
Name: slack-cache
Version: 1.0.1
Summary: Cached Slack API
Home-page: https://github.com/carlskeide/slack-cache
Author: Carl Skeide
Author-email: carl@skeide.se
License: MIT
Download-URL: https://github.com/carlskeide/slack-cache/archive/1.0.1.tar.gz
Keywords: slack
Platform: UNKNOWN
